proximityhash.py
proximityhash-3.0.1.dist-info/LICENSE
proximityhash-3.0.1.dist-info/METADATA
proximityhash-3.0.1.dist-info/WHEEL
proximityhash-3.0.1.dist-info/entry_points.txt
proximityhash-3.0.1.dist-info/top_level.txt
proximityhash-3.0.1.dist-info/RECORD
