Metadata-Version: 2.1
Name: proximityhash
Version: 3.0.1
Summary: Geohashes in proximity
Home-page: https://github.com/ashwin711/proximityhash
Download-URL: https://github.com/ashwin711/proximityhash/tarball/3.0.0
Author: Ashwin Nair
Author-email: ashwinnair.ua@gmail.com
License: MIT
Keywords: geohash,optimizer,compression,geo,latitude,longitude,coordinates,proximity,circle
Classifier: Development Status :: 5 - Production/Stable
Classifier: Environment :: Console
Classifier: Intended Audience :: Developers
Classifier: License :: OSI Approved :: Apache Software License
Classifier: Programming Language :: Python
Classifier: Topic :: Software Development :: Libraries :: Python Modules
Classifier: Topic :: Utilities
License-File: LICENSE
Requires-Dist: clint
Requires-Dist: argparse
Requires-Dist: georaptor >=3.0.0
Requires-Dist: geohash2
